[
 {
  "add_signature": 0,
  "always_use_account_email_id_as_sender": 0,
  "always_use_account_name_as_sender_name": 0,
  "append_emails_to_sent_folder": 0,
  "append_to": "Opportunity",
  "ascii_encode_password": 0,
  "attachment_limit": 0,
  "auth_method": "Basic",
  "auto_reply_message": null,
  "awaiting_password": 0,
  "brand_logo": null,
  "connected_app": null,
  "connected_user": null,
  "create_contact": 1,
  "default_incoming": 0,
  "default_outgoing": 0,
  "docstatus": 0,
  "doctype": "Email Account",
  "domain": null,
  "email_account_name": "Sales",
  "email_id": "sales@example.com",
  "email_server": null,
  "email_sync_option": "UNSEEN",
  "enable_auto_reply": 0,
  "enable_automatic_linking": 0,
  "enable_incoming": 0,
  "enable_outgoing": 0,
  "footer": null,
  "imap_folder": [],
  "incoming_port": null,
  "initial_sync_count": "250",
  "login_id": null,
  "login_id_is_different": 0,
  "modified": "2024-05-23 22:35:50.259234",
  "name": "Sales",
  "no_failed": 0,
  "no_smtp_authentication": 0,
  "notify_if_unreplied": 0,
  "password": null,
  "send_notification_to": null,
  "send_unsubscribe_message": 1,
  "service": "",
  "signature": null,
  "smtp_port": null,
  "smtp_server": null,
  "track_email_status": 1,
  "uidnext": 0,
  "uidvalidity": null,
  "unreplied_for_mins": 30,
  "use_imap": 0,
  "use_ssl": 0,
  "use_ssl_for_outgoing": 0,
  "use_starttls": 0,
  "use_tls": 0
 },
 {
  "add_signature": 0,
  "always_use_account_email_id_as_sender": 0,
  "always_use_account_name_as_sender_name": 0,
  "append_emails_to_sent_folder": 0,
  "append_to": "Issue",
  "ascii_encode_password": 0,
  "attachment_limit": 0,
  "auth_method": "Basic",
  "auto_reply_message": null,
  "awaiting_password": 0,
  "brand_logo": null,
  "connected_app": null,
  "connected_user": null,
  "create_contact": 1,
  "default_incoming": 0,
  "default_outgoing": 0,
  "docstatus": 0,
  "doctype": "Email Account",
  "domain": null,
  "email_account_name": "Support",
  "email_id": "support@example.com",
  "email_server": null,
  "email_sync_option": "UNSEEN",
  "enable_auto_reply": 0,
  "enable_automatic_linking": 0,
  "enable_incoming": 0,
  "enable_outgoing": 0,
  "footer": null,
  "imap_folder": [],
  "incoming_port": null,
  "initial_sync_count": "250",
  "login_id": null,
  "login_id_is_different": 0,
  "modified": "2024-05-23 22:35:50.284715",
  "name": "Support",
  "no_failed": 0,
  "no_smtp_authentication": 0,
  "notify_if_unreplied": 0,
  "password": null,
  "send_notification_to": null,
  "send_unsubscribe_message": 1,
  "service": "",
  "signature": null,
  "smtp_port": null,
  "smtp_server": null,
  "track_email_status": 1,
  "uidnext": 0,
  "uidvalidity": null,
  "unreplied_for_mins": 30,
  "use_imap": 0,
  "use_ssl": 0,
  "use_ssl_for_outgoing": 0,
  "use_starttls": 0,
  "use_tls": 0
 },
 {
  "add_signature": 0,
  "always_use_account_email_id_as_sender": 0,
  "always_use_account_name_as_sender_name": 0,
  "append_emails_to_sent_folder": 0,
  "append_to": null,
  "ascii_encode_password": 0,
  "attachment_limit": 0,
  "auth_method": "Basic",
  "auto_reply_message": null,
  "awaiting_password": 0,
  "brand_logo": null,
  "connected_app": null,
  "connected_user": null,
  "create_contact": 1,
  "default_incoming": 0,
  "default_outgoing": 0,
  "docstatus": 0,
  "doctype": "Email Account",
  "domain": null,
  "email_account_name": "Email Linking",
  "email_id": "email_linking@example.com",
  "email_server": null,
  "email_sync_option": "UNSEEN",
  "enable_auto_reply": 0,
  "enable_automatic_linking": 0,
  "enable_incoming": 0,
  "enable_outgoing": 0,
  "footer": null,
  "imap_folder": [],
  "incoming_port": null,
  "initial_sync_count": "250",
  "login_id": null,
  "login_id_is_different": 0,
  "modified": "2024-05-23 22:36:42.363590",
  "name": "Email Linking",
  "no_failed": 0,
  "no_smtp_authentication": 0,
  "notify_if_unreplied": 0,
  "password": null,
  "send_notification_to": null,
  "send_unsubscribe_message": 1,
  "service": "",
  "signature": null,
  "smtp_port": null,
  "smtp_server": null,
  "track_email_status": 1,
  "uidnext": 0,
  "uidvalidity": null,
  "unreplied_for_mins": 30,
  "use_imap": 0,
  "use_ssl": 0,
  "use_ssl_for_outgoing": 0,
  "use_starttls": 0,
  "use_tls": 0
 },
 {
  "add_signature": 0,
  "always_use_account_email_id_as_sender": 0,
  "always_use_account_name_as_sender_name": 0,
  "append_emails_to_sent_folder": 0,
  "append_to": null,
  "ascii_encode_password": 0,
  "attachment_limit": 0,
  "auth_method": "Basic",
  "auto_reply_message": null,
  "awaiting_password": 0,
  "brand_logo": null,
  "connected_app": null,
  "connected_user": null,
  "create_contact": 1,
  "default_incoming": 0,
  "default_outgoing": 0,
  "docstatus": 0,
  "doctype": "Email Account",
  "domain": "example.com",
  "email_account_name": "Notifications",
  "email_id": "notifications@example.com",
  "email_server": "imap.example.com",
  "email_sync_option": "UNSEEN",
  "enable_auto_reply": 0,
  "enable_automatic_linking": 0,
  "enable_incoming": 0,
  "enable_outgoing": 0,
  "footer": null,
  "imap_folder": [],
  "incoming_port": null,
  "initial_sync_count": "250",
  "login_id": null,
  "login_id_is_different": 0,
  "modified": "2024-05-24 00:54:10.509817",
  "name": "Notifications",
  "no_failed": 0,
  "no_smtp_authentication": 0,
  "notify_if_unreplied": 0,
  "password": null,
  "send_notification_to": null,
  "send_unsubscribe_message": 1,
  "service": "",
  "signature": null,
  "smtp_port": null,
  "smtp_server": "smtp.example.com",
  "track_email_status": 1,
  "uidnext": 0,
  "uidvalidity": null,
  "unreplied_for_mins": 30,
  "use_imap": 1,
  "use_ssl": 0,
  "use_ssl_for_outgoing": 0,
  "use_starttls": 0,
  "use_tls": 0
 },
 {
  "add_signature": 0,
  "always_use_account_email_id_as_sender": 0,
  "always_use_account_name_as_sender_name": 0,
  "append_emails_to_sent_folder": 0,
  "append_to": null,
  "ascii_encode_password": 0,
  "attachment_limit": 0,
  "auth_method": "Basic",
  "auto_reply_message": null,
  "awaiting_password": 0,
  "brand_logo": null,
  "connected_app": null,
  "connected_user": null,
  "create_contact": 1,
  "default_incoming": 0,
  "default_outgoing": 0,
  "docstatus": 0,
  "doctype": "Email Account",
  "domain": "example.com",
  "email_account_name": "Replies",
  "email_id": "replies@example.com",
  "email_server": "imap.example.com",
  "email_sync_option": "UNSEEN",
  "enable_auto_reply": 0,
  "enable_automatic_linking": 0,
  "enable_incoming": 0,
  "enable_outgoing": 0,
  "footer": null,
  "imap_folder": [],
  "incoming_port": null,
  "initial_sync_count": "250",
  "login_id": null,
  "login_id_is_different": 0,
  "modified": "2024-05-24 00:54:10.525142",
  "name": "Replies",
  "no_failed": 0,
  "no_smtp_authentication": 0,
  "notify_if_unreplied": 0,
  "password": null,
  "send_notification_to": null,
  "send_unsubscribe_message": 1,
  "service": "",
  "signature": null,
  "smtp_port": null,
  "smtp_server": "smtp.example.com",
  "track_email_status": 1,
  "uidnext": 0,
  "uidvalidity": null,
  "unreplied_for_mins": 30,
  "use_imap": 1,
  "use_ssl": 0,
  "use_ssl_for_outgoing": 0,
  "use_starttls": 0,
  "use_tls": 0
 },
 {
  "add_signature": 0,
  "always_use_account_email_id_as_sender": 1,
  "always_use_account_name_as_sender_name": 1,
  "append_emails_to_sent_folder": 0,
  "append_to": null,
  "ascii_encode_password": 0,
  "attachment_limit": 25,
  "auth_method": "Basic",
  "auto_reply_message": null,
  "awaiting_password": 1,
  "brand_logo": null,
  "connected_app": null,
  "connected_user": null,
  "create_contact": 1,
  "default_incoming": 0,
  "default_outgoing": 1,
  "docstatus": 0,
  "doctype": "Email Account",
  "domain": null,
  "email_account_name": "psa",
  "email_id": "psa.yemen.2024@gmail.com",
  "email_server": "imap.gmail.com",
  "email_sync_option": "UNSEEN",
  "enable_auto_reply": 0,
  "enable_automatic_linking": 0,
  "enable_incoming": 0,
  "enable_outgoing": 1,
  "footer": null,
  "imap_folder": [
   {
    "append_to": null,
    "folder_name": "INBOX",
    "parent": "psa",
    "parentfield": "imap_folder",
    "parenttype": "Email Account",
    "uidnext": "13",
    "uidvalidity": "1"
   }
  ],
  "incoming_port": "993",
  "initial_sync_count": "250",
  "login_id": null,
  "login_id_is_different": 0,
  "modified": "2024-05-26 23:21:37.494481",
  "name": "psa",
  "no_failed": 9,
  "no_smtp_authentication": 0,
  "notify_if_unreplied": 0,
  "password": "yznbypuktduxyhbh",
  "send_notification_to": null,
  "send_unsubscribe_message": 1,
  "service": "GMail",
  "signature": null,
  "smtp_port": "587",
  "smtp_server": "smtp.gmail.com",
  "track_email_status": 1,
  "uidnext": 13,
  "uidvalidity": null,
  "unreplied_for_mins": 30,
  "use_imap": 1,
  "use_ssl": 1,
  "use_ssl_for_outgoing": 0,
  "use_starttls": 0,
  "use_tls": 1
 }
]
